sparqlprog.py
sparqlprog-0.0.3.dist-info/LICENSE
sparqlprog-0.0.3.dist-info/METADATA
sparqlprog-0.0.3.dist-info/WHEEL
sparqlprog-0.0.3.dist-info/top_level.txt
sparqlprog-0.0.3.dist-info/RECORD
